pylibfranka/README.md
pylibfranka/VERSION
pylibfranka/__init__.py
pylibfranka/_pylibfranka.cpython-39-x86_64-linux-gnu.so
pylibfranka/_version.py
pylibfranka/libfranka.so
pylibfranka/libfranka.so.0.20
pylibfranka/libfranka.so.0.20.3
pylibfranka.libs/libPocoFoundation-ea3c5834.so.62
pylibfranka.libs/libPocoNet-44776267.so.62
pylibfranka.libs/libfranka-bfefa7cb.so.0.20.3
pylibfranka.libs/libpcre-fb2fc875.so.3.13.3
pylibfranka-0.20.3.dist-info/METADATA
pylibfranka-0.20.3.dist-info/WHEEL
pylibfranka-0.20.3.dist-info/top_level.txt
pylibfranka-0.20.3.dist-info/RECORD
pylibfranka-0.20.3.dist-info/licenses/LICENSE
pylibfranka-0.20.3.dist-info/licenses/NOTICE
