Metadata-Version: 2.4
Name: pylibfranka
Version: 0.20.3
Summary: Python bindings for libfranka - Control Franka robots with Python
Author-email: Franka Robotics GmbH <info@franka.de>
License: Apache-2.0
Project-URL: Homepage, https://github.com/frankarobotics/libfranka
Project-URL: Documentation, https://frankarobotics.github.io/libfranka/pylibfranka/latest
Project-URL: Repository, https://github.com/frankarobotics/libfranka
Project-URL: Issues, https://github.com/frankarobotics/libfranka/issues
Project-URL: Changelog, https://github.com/frankarobotics/libfranka/blob/main/CHANGELOG.md
Classifier: Development Status :: 4 - Beta
Classifier: Intended Audience :: Developers
Classifier: Intended Audience :: Science/Research
Classifier: License :: OSI Approved :: Apache Software License
Classifier: Operating System :: POSIX :: Linux
Classifier: Programming Language :: Python :: 3
Classifier: Programming Language :: Python :: 3.9
Classifier: Programming Language :: Python :: 3.10
Classifier: Programming Language :: Python :: 3.11
Classifier: Programming Language :: Python :: 3.12
Classifier: Programming Language :: C++
Classifier: Topic :: Software Development :: Libraries :: Python Modules
Requires-Python: >=3.9
License-File: LICENSE
License-File: NOTICE
Requires-Dist: numpy>=1.19.0
Provides-Extra: dev
Requires-Dist: pre-commit>=3.3.2; extra == "dev"
Requires-Dist: black>=23.3.0; extra == "dev"
Requires-Dist: isort>=5.12.0; extra == "dev"
Requires-Dist: flake8>=6.0.0; extra == "dev"
Requires-Dist: flake8-docstrings>=1.7.0; extra == "dev"
Requires-Dist: mypy>=1.3.0; extra == "dev"
Requires-Dist: pytest>=7.3.1; extra == "dev"
Dynamic: license-file
Dynamic: requires-python
